clinica/__init__.py
clinica/cmdline.py
clinica/compat.py
clinica/converters/__init__.py
clinica/converters/_utils.py
clinica/converters/abstract_converter.py
clinica/converters/adni_to_bids/__init__.py
clinica/converters/adni_to_bids/_converter.py
clinica/converters/adni_to_bids/_json.py
clinica/converters/adni_to_bids/_utils.py
clinica/converters/adni_to_bids/cli.py
clinica/converters/adni_to_bids/modality_converters/__init__.py
clinica/converters/adni_to_bids/modality_converters/_av45_fbb_pet.py
clinica/converters/adni_to_bids/modality_converters/_dwi.py
clinica/converters/adni_to_bids/modality_converters/_factory.py
clinica/converters/adni_to_bids/modality_converters/_fdg_pet.py
clinica/converters/adni_to_bids/modality_converters/_flair.py
clinica/converters/adni_to_bids/modality_converters/_fmap.py
clinica/converters/adni_to_bids/modality_converters/_fmri.py
clinica/converters/adni_to_bids/modality_converters/_image_path_utils.py
clinica/converters/adni_to_bids/modality_converters/_path_to_bids.py
clinica/converters/adni_to_bids/modality_converters/_pet_utils.py
clinica/converters/adni_to_bids/modality_converters/_pib_pet.py
clinica/converters/adni_to_bids/modality_converters/_qc_utils.py
clinica/converters/adni_to_bids/modality_converters/_t1.py
clinica/converters/adni_to_bids/modality_converters/_tau_pet.py
clinica/converters/adni_to_bids/modality_converters/_visits_utils.py
clinica/converters/adni_to_bids/specifications/participant.tsv
clinica/converters/adni_to_bids/specifications/scans.tsv
clinica/converters/adni_to_bids/specifications/sessions.tsv
clinica/converters/aibl_to_bids/__init__.py
clinica/converters/aibl_to_bids/_converter.py
clinica/converters/aibl_to_bids/cli.py
clinica/converters/aibl_to_bids/utils/__init__.py
clinica/converters/aibl_to_bids/utils/bids.py
clinica/converters/aibl_to_bids/utils/clinical.py
clinica/converters/aibl_to_bids/utils/json.py
clinica/converters/cli.py
clinica/converters/cli_param.py
clinica/converters/factory.py
clinica-0.10.1.dist-info/LICENSE.txt
clinica-0.10.1.dist-info/METADATA
clinica-0.10.1.dist-info/WHEEL
clinica-0.10.1.dist-info/entry_points.txt
clinica-0.10.1.dist-info/RECORD
