Metadata-Version: 2.3
Name: clinica
Version: 0.10.1
Summary: Software platform for clinical neuroimaging studies
License: MIT
Keywords: bids,image processing,machine learning,neuroimaging,neuroscience
Author: ARAMIS Lab
Maintainer: Clinica developers
Maintainer-email: clinica.run@gmail.com>
Requires-Python: >=3.9,<3.13
Classifier: Development Status :: 4 - Beta
Classifier: Environment :: Console
Classifier: Intended Audience :: Developers
Classifier: Intended Audience :: End Users/Desktop
Classifier: Operating System :: OS Independent
Classifier: Topic :: Scientific/Engineering :: Medical Science Apps.
Classifier: Topic :: Scientific/Engineering :: Image Processing
Requires-Dist: antspyx (>=0.4.2)
Requires-Dist: argcomplete (>=1.9.4,<2)
Requires-Dist: attrs (>=20.1.0)
Requires-Dist: cattrs
Requires-Dist: click
Requires-Dist: click-option-group (>=0.5,<1.0)
Requires-Dist: colorlog (>=5,<6)
Requires-Dist: fsspec
Requires-Dist: jinja2 (>=3,<4)
Requires-Dist: joblib (>=1.2.0,<2.0)
Requires-Dist: matplotlib
Requires-Dist: networkx
Requires-Dist: nibabel (>=5)
Requires-Dist: nilearn (>=0.10.3,<1.0)
Requires-Dist: nipype (>=1.8.6)
Requires-Dist: numpy (>=2,<3)
Requires-Dist: openpyxl
Requires-Dist: pandas (>=2,<3)
Requires-Dist: pybids (>=0.16,<1.0)
Requires-Dist: pydicom
Requires-Dist: pydra (>=0.22,<0.23)
Requires-Dist: pydra-bids (>=0.0.10)
Requires-Dist: pydra-freesurfer (>=0.0.9)
Requires-Dist: pydra-fsl (>=0.0.22)
Requires-Dist: pydra-nipype1
Requires-Dist: pydra-petpvc (>=0.0.4)
Requires-Dist: rich (>=13.8.0)
Requires-Dist: scikit-image
Requires-Dist: scikit-learn (>=1.0,<2)
Requires-Dist: scipy (>=1.12,<2)
Requires-Dist: xgboost
Requires-Dist: xlrd
Requires-Dist: xvfbwrapper
Project-URL: Documentation, https://aramislab.paris.inria.fr/clinica/docs/public/latest
Project-URL: Homepage, https://www.clinica.run
Project-URL: issues, https://github.com/aramis-lab/clinica/issues
Project-URL: sources, https://github.com/aramis-lab/clinica
